<?xml version="1.0" encoding="UTF-8"?><metadata xmlns:xsi="http://www.w3.org/2001/XMLSchema-instance" xsi:noNamespaceSchemaLocation="http://www.conabio.gob.mx/informacion/gis/schemas/fgdc/fgdc-std-001-1998.xsd"><idinfo><citation><citeinfo><origin>Comisi&#x00F3;n Nacional para el Conocimiento y Uso de la Biodiversidad (CONABIO), (1998). &apos;Curvas de nivel para la Rep&#x00FA;blica Mexicana&apos;. Escala 1:250000. Extra&#x00ED;do del Modelo Digital del Terreno. Instituto Nacional de Estad&#x00ED;stica, Geograf&#x00ED;a e Inform&#x00E1;tica (INEG). M&#x00E9;xico.</origin><pubdate>20010511</pubdate><title>Curvas de nivel para la Rep&#x00FA;blica Mexicana</title><geoform>Shapefile. Formato vectorial compuesto por 4 archivos (shp, shx, dbf,prj)</geoform><othercit>250000</othercit></citeinfo></citation><descript><abstract>Este mapa presenta las curvas de nivel del pa&#x00ED;s cada 200 metros; extra&#x00ED;do del Modelo Digital del Terreno escala 1:250000 de INEGI.</abstract><purpose>No conocido</purpose></descript><timeperd><timeinfo><sngdate><caldate>00000000</caldate></sngdate></timeinfo><current>No conocido</current></timeperd><status><progress>Complete</progress><update>No planeado</update></status><spdom><bounding><westbc>-117.105699</westbc><eastbc>-88.860935</eastbc><northbc>32.644634</northbc><southbc>14.895714</southbc></bounding></spdom><keywords><theme><themekt>ESTRUCTURA</themekt><themekey>topog</themekey><themekey>terrest</themekey><themekey>cni250kgw</themekey></theme><theme><themekt>CONABIO</themekt><themekey>Topograf&#x00ED;a Terrestre 1:250000 Aspecto fisico Topografia </themekey></theme><place><placekt>CONABIO</placekt><placekey>Nacional </placekey></place></keywords><accconst>Sin restricciones</accconst><useconst>Sin restricciones</useconst><browse><browsen>http://www.conabio.gob.mx/informacion/gis/layouts/cni250kgw.png</browsen><browsed>Mapa ilustrativo de Curvas de nivel para la Rep&#x00FA;blica Mexicana</browsed><browset>png</browset></browse><native>SIG ARC-INFO, versi&#x00F3;n 9.2 y SUNW,Sun-Fire-V890; sparc; sun4u, UNIX</native></idinfo><dataqual><logic>Laboratorio</logic><complete>No conocido</complete><lineage><procstep><procdesc>El mapa fue elaborado a trav&#x00E9;s del SIG ARC-INFO.</procdesc><procdate>00000000</procdate></procstep></lineage></dataqual><spdoinfo><direct>Vector</direct><ptvctinf><sdtsterm ><sdtstype>Ring composed of arcs</sdtstype><ptvctcnt>81097</ptvctcnt></sdtsterm></ptvctinf></spdoinfo><spref><horizsys><geograph><latres>0.0174532925199433</latres><longres>0.0174532925199433</longres><geogunit>Decimal degrees</geogunit></geograph><geodetic><horizdn>WGS84</horizdn><ellips>WGS84</ellips><semiaxis>6378137.000000</semiaxis><denflat>298.257224</denflat></geodetic></horizsys></spref><eainfo><detailed><enttyp><enttypl>CNI250KGW.DBF</enttypl><enttypd>Curvas de nivel a escala 1:250000</enttypd><enttypds>No conocido</enttypds></enttyp><attr><attrlabl>Length</attrlabl><attrdef>Num&#x00E9;rico</attrdef><attrdefs>Calculado por Arc-Info</attrdefs><attrdomv><udom>Longitud de la curva de nivel.</udom></attrdomv><attrvai><attrva>1</attrva><attrvae>Grados decimales</attrvae></attrvai></attr><attr><attrlabl>Contour</attrlabl><attrdef>Num&#x00E9;rico</attrdef><attrdefs>Datos del proyecto</attrdefs><attrdomv><udom>Altitud de la curva de nivel.</udom></attrdomv><attrvai><attrva>1</attrva><attrvae>Metros sobre el nivel del mar (m.s.n.m.)</attrvae></attrvai></attr></detailed></eainfo><distinfo><distrib><cntinfo><cntorgp><cntorg>CONABIO</cntorg><cntper>Jose Manuel Davila Rosas</cntper></cntorgp><cntpos>Subdirector de Sistemas de Informaci&#x00F3;n Geogr&#x00E1;fica</cntpos><cntaddr><addrtype>mailing and physical address</addrtype><address>Liga Perif&#x00E9;rico Insurgentes Sur Num. 4903 1er piso. Col. Parques del Pedregal. Delg. Tlalpan</address><city>Ciudad de M&#x00E9;xico</city><state>D.F.</state><postal>14010</postal><country>M&#x00E9;xico</country></cntaddr><cntvoice>50045012</cntvoice><cntfax>50044931</cntfax><cntemail>jdavila@conabio.gob.mx</cntemail><hours>Lunes a Viernes de las 8 hasta 18 hrs.</hours></cntinfo></distrib><resdesc>cni250kgw</resdesc><distliab>No se permite utilizar estos datos con fines lucrativos y se debe citar la fuente del mapa y a CONABIO. La Subdirecci&#x00F3;n de Sistemas de Informaci&#x00F3;n Geogr&#x00E1;fica de la CONABIO solo se hace responsable de la informaci&#x00F3;n presentada en el mapa y se deslinda del uso que se le de a la misma.</distliab><stdorder><digform><digtinfo><formname>ESRI Shapefile(SHP)</formname><formverd>199807</formverd><filedec>compactado en ZIP</filedec><transize>53.63</transize></digtinfo><digtopt><onlinopt><computer><networka><networkr> http://www.conabio.gob.mx/informacion/gis/maps/geo/cni250kgw.zip</networkr></networka></computer><accinstr>Coordenadas geogr&#x00E1;ficas WGS84. (EPSG:4326). Formato vectorial de almacenamiento de elementos geogr&#x00E1;ficos y sus atributos asociados. </accinstr></onlinopt><onlinopt><computer><networka><networkr> http://www.conabio.gob.mx/informacion/gis/maps/ccl/cni250kgw_c.zip</networkr></networka></computer><accinstr>Proyecci&#x00F3;n C&#x00F3;nica Conforme de Lambert WGS84. (EPSG:48402). Formato vectorial de almacenamiento de elementos geogr&#x00E1;ficos y sus atributos asociados. </accinstr></onlinopt></digtopt></digform><digform><digtinfo><formname>Google Earth KML</formname><formvern>2.2</formvern><filedec>compactado como KMZ</filedec></digtinfo><digtopt><onlinopt><computer><networka><networkr>  http://www.conabio.gob.mx/informacion/explorer/wms/kml?layers=cni250kgw&amp;mode=download&amp;legend=true</networkr></networka></computer><accinstr>Coordenadas geogr&#x00E1;ficas WGS84. (EPSG:4326). Los archivos KML representan datos geogr&#x00E1;ficos para Google Earth, a menudo suelen distribuirse comprimidos como KMZ.</accinstr></onlinopt></digtopt></digform><digform><digtinfo><formname>Servicio de im&#x00E1;genes (WMS)</formname><formvern>1.1.1</formvern></digtinfo><digtopt><onlinopt><computer><networka><networkr>http://www.conabio.gob.mx/informacion/explorer/wms?Format=image.png&amp;request=GetMap&amp;version=1.1.1&amp;width=800&amp;height=424&amp;srs=EPSG:4326&amp;bbox=-120.0,13.8,-85.1,33.5&amp;layers=cni250kgw</networkr></networka></computer><accinstr>Coordenadas geogr&#x00E1;ficas WGS84. (EPSG:4326). Servicio Web Map Service. Los mapas de datos referenciados espacialmente producidos se generan normalmente en un formato de imagen como PNG,.png o JPEG, pueden se vistos en un SIG </accinstr></onlinopt></digtopt></digform><fees>Acceso libre sin ning&#x00FA;n cargo al p&#x00FA;blico en general.</fees></stdorder><techpreq>Tener Arc/info, Arcview o sistemas compatibles, en caso que existan se pueden visualizar en Google Earth KML y/o conexi&#x00F3;n al servicio WMS.</techpreq></distinfo><metainfo><metd>20080306</metd><metc><cntinfo><cntorgp><cntorg>CONABIO</cntorg></cntorgp><cntpos>Pedro Diaz</cntpos><cntaddr><addrtype>mailing and physical address</addrtype><address>Liga Perif&#x00E9;rico Insurgentes Sur Num. 4903 1er piso. Col. Parques del Pedregal. Delg. Tlalpan</address><city>Ciudad de M&#x00E9;xico</city><state>D.F.</state><postal>14010</postal><country>M&#x00E9;xico</country></cntaddr><cntvoice>50045018 50044938</cntvoice><cntfax>50044931</cntfax><cntemail>ssig@conabio.gob.mx</cntemail><hours>Lunes a Viernes de 8 a 18 hrs.</hours></cntinfo></metc><metstdn>FGDC Content Standards for Digital Geospatial Metadata, 1998</metstdn><metstdv>FGDC-STD-001-1998 version 2.0</metstdv></metainfo></metadata>